{"paging":{"total":42,"offset":0,"limit":50,"returned":42},"stores":[{"distance":15.9636,"store":{"id":"1007831","name":"Dogwood Plaza - Gatlinburg","brandName":"Starbucks","phoneNumber":"865-325-1545","operatingStatus":{"operating":true,"openDate":"9/8/2014 12:00:00 AM","closeDate":null,"status":"ACTIVE"},"address":{"streetAddressLine1":"903 Parkway","streetAddressLine2":"101","streetAddressLine3":null,"city":"Gatlinburg","countrySubdivisionCode":"TN","countryCode":"US","postalCode":"37738"},"coordinates":{"latitude":35.710991,"longitude":-83.518881},"features":[],"regularHours":null,"today":null,"currency":"USD"}},{"distance":20.9152,"store":{"id":"10733","name":"Western Carolina University -C","brandName":"Starbucks","phoneNumber":null,"operatingStatus":{"operating":true,"openDate":"6/29/2009 12:00:00 AM","closeDate":null,"status":"ACTIVE"},"address":{"streetAddressLine1":"517 Centennial Drive","streetAddressLine2":null,"streetAddressLine3":null,"city":"Cullowhee","countrySubdivisionCode":"NC","countryCode":"US","postalCode":"28723"},"coordinates":{"latitude":35.309831,"longitude":-83.183592},"features":[{"code":"WF","name":"Wireless Hotspot"},{"code":"LB","name":"La Boulange"}],"regularHours":{"monday":{"open":true,"open24Hours":false,"openTime":"07:30:00","closeTime":"01:00:00"},"tuesday":{"open":true,"open24Hours":false,"openTime":"07:30:00","closeTime":"01:00:00"},"wednesday":{"open":true,"open24Hours":false,"openTime":"07:30:00","closeTime":"01:00:00"},"thursday":{"open":true,"open24Hours":false,"openTime":"07:30:00","closeTime":"01:00:00"},"friday":{"open":true,"open24Hours":false,"openTime":"07:30:00","closeTime":"01:00:00"},"saturday":{"open":true,"open24Hours":false,"openTime":"09:00:00","closeTime":"16:00:00"},"sunday":{"open":true,"open24Hours":false,"openTime":"09:00:00","closeTime":"01:00:00"},"open24x7":false},"today":{"open":true,"open24Hours":false,"openTime":"07:30:00","closeTime":"01:00:00","localTime":"2014-09-24T17:43:12.5998399","openAsOfLocalTime":true,"opensIn":null,"closesIn":"07:16:47"},"currency":"USD"}},{"distance":22.9204,"store":{"id":"10490","name":"Kroger-Pigeon Forge #536","brandName":"Starbucks","phoneNumber":"865-429-0874","operatingStatus":{"operating":true,"openDate":"3/17/2008 12:00:00 AM","closeDate":null,"status":"ACTIVE"},"address":{"streetAddressLine1":"220 Wears Valley Road","streetAddressLine2":null,"streetAddressLine3":null,"city":"Pigeon Forge","countrySubdivisionCode":"TN","countryCode":"US","postalCode":"378634215"},"coordinates":{"latitude":35.804494,"longitude":-83.581951},"features":[{"code":"WF","name":"Wireless Hotspot"},{"code":"LB","name":"La Boulange"}],"regularHours":{"monday":{"open":true,"open24Hours":false,"openTime":"07:00:00","closeTime":"21:30:00"},"tuesday":{"open":true,"open24Hours":false,"openTime":"07:00:00","closeTime":"21:30:00"},"wednesday":{"open":true,"open24Hours":false,"openTime":"07:00:00","closeTime":"21:30:00"},"thursday":{"open":true,"open24Hours":false,"openTime":"07:00:00","closeTime":"21:30:00"},"friday":{"open":true,"open24Hours":false,"openTime":"07:00:00","closeTime":"21:30:00"},"saturday":{"open":true,"open24Hours":false,"openTime":"07:00:00","closeTime":"21:30:00"},"sunday":{"open":true,"open24Hours":false,"openTime":"07:00:00","closeTime":"21:30:00"},"open24x7":false},"today":{"open":true,"open24Hours":false,"openTime":"07:00:00","closeTime":"21:30:00","localTime":"2014-09-24T17:43:12.5998399","openAsOfLocalTime":true,"opensIn":null,"closesIn":"03:46:47"},"currency":"USD"}},{"distance":23.0116,"store":{"id":"18328","name":"Parkway & Wears Valley Road","brandName":"Starbucks","phoneNumber":"(865) 429-3124","operatingStatus":{"operating":true,"openDate":"6/29/2007 12:00:00 AM","closeDate":null,"status":"ACTIVE"},"address":{"streetAddressLine1":"2491 HIGHWAY 441","streetAddressLine2":null,"streetAddressLine3":null,"city":"Pigeon Forge","countrySubdivisionCode":"TN","countryCode":"US","postalCode":"37863"},"coordinates":{"latitude":35.806675,"longitude":-83.577475},"features":[{"code":"WA","name":"Oven-warmed Food"},{"code":"WF","name":"Wireless Hotspot"},{"code":"VS","name":"Verismo"},{"code":"CD","name":"Mobile Payment"},{"code":"DR","name":"Digital Rewards"},{"code":"LB","name":"La Boulange"},{"code":"DT","name":"Drive-Through"}],"regularHours":{"monday":{"open":true,"open24Hours":false,"openTime":"06:00:00","closeTime":"23:00:00"},"tuesday":{"open":true,"open24Hours":false,"openTime":"06:00:00","closeTime":"23:00:00"},"wednesday":{"open":true,"open24Hours":false,"openTime":"06:00:00","closeTime":"23:00:00"},"thursday":{"open":true,"open24Hours":false,"openTime":"06:00:00","closeTime":"23:00:00"},"friday":{"open":true,"open24Hours":false,"openTime":"06:00:00","closeTime":"00:00:00"},"saturday":{"open":true,"open24Hours":false,"openTime":"06:00:00","closeTime":"00:00:00"},"sunday":{"open":true,"open24Hours":false,"openTime":"06:00:00","closeTime":"23:00:00"},"open24x7":false},"today":{"open":true,"open24Hours":false,"openTime":"06:00:00","closeTime":"23:00:00","localTime":"2014-09-24T17:43:12.5998399","openAsOfLocalTime":true,"opensIn":null,"closesIn":"05:16:47"},"currency":"USD"}},{"distance":24.3244,"store":{"id":"15100","name":"US Hwy 441 & New Era","brandName":"Starbucks","phoneNumber":"865-429-1210","operatingStatus":{"operating":true,"openDate":"12/6/2002 12:00:00 AM","closeDate":null,"status":"ACTIVE"},"address":{"streetAddressLine1":"1645 Parkway","streetAddressLine2":"Unit 103","streetAddressLine3":null,"city":"Sevierville","countrySubdivisionCode":"TN","countryCode":"US","postalCode":"378622899"},"coordinates":{"latitude":35.826553,"longitude":-83.57504},"features":[{"code":"WA","name":"Oven-warmed Food"},{"code":"WF","name":"Wireless Hotspot"},{"code":"VS","name":"Verismo"},{"code":"CD","name":"Mobile Payment"},{"code":"DR","name":"Digital Rewards"},{"code":"LB","name":"La Boulange"}],"regularHours":{"monday":{"open":true,"open24Hours":false,"openTime":"07:00:00","closeTime":"21:00:00"},"tuesday":{"open":true,"open24Hours":false,"openTime":"07:00:00","closeTime":"21:00:00"},"wednesday":{"open":true,"open24Hours":false,"openTime":"07:00:00","closeTime":"21:00:00"},"thursday":{"open":true,"open24Hours":false,"openTime":"07:00:00","closeTime":"21:00:00"},"friday":{"open":true,"open24Hours":false,"openTime":"07:00:00","closeTime":"21:00:00"},"saturday":{"open":true,"open24Hours":false,"openTime":"07:00:00","closeTime":"21:00:00"},"sunday":{"open":true,"open24Hours":false,"openTime":"07:00:00","closeTime":"19:00:00"},"open24x7":false},"today":{"open":true,"open24Hours":false,"openTime":"07:00:00","closeTime":"21:00:00","localTime":"2014-09-24T17:43:12.5998399","openAsOfLocalTime":true,"opensIn":null,"closesIn":"03:16:47"},"currency":"USD"}},{"distance":27.9711,"store":{"id":"8266","name":"Hwy 66 & US 411","brandName":"Starbucks","phoneNumber":"865-429-2650","operatingStatus":{"operating":true,"openDate":"8/13/2005 12:00:00 AM","closeDate":null,"status":"ACTIVE"},"address":{"streetAddressLine1":"646 Winfield Dunn Parkway","streetAddressLine2":null,"streetAddressLine3":null,"city":"Sevierville","countrySubdivisionCode":"TN","countryCode":"US","postalCode":"378765510"},"coordinates":{"latitude":35.880623,"longitude":-83.573225},"features":[{"code":"WA","name":"Oven-warmed Food"},{"code":"WF","name":"Wireless Hotspot"},{"code":"CD","name":"Mobile Payment"},{"code":"DR","name":"Digital Rewards"},{"code":"LB","name":"La Boulange"},{"code":"DT","name":"Drive-Through"}],"regularHours":{"monday":{"open":true,"open24Hours":false,"openTime":"06:00:00","closeTime":"22:00:00"},"tuesday":{"open":true,"open24Hours":false,"openTime":"06:00:00","closeTime":"22:00:00"},"wednesday":{"open":true,"open24Hours":false,"openTime":"06:00:00","closeTime":"22:00:00"},"thursday":{"open":true,"open24Hours":false,"openTime":"06:00:00","closeTime":"22:00:00"},"friday":{"open":true,"open24Hours":false,"openTime":"06:00:00","closeTime":"23:00:00"},"saturday":{"open":true,"open24Hours":false,"openTime":"06:00:00","closeTime":"23:00:00"},"sunday":{"open":true,"open24Hours":false,"openTime":"06:00:00","closeTime":"22:00:00"},"open24x7":false},"today":{"open":true,"open24Hours":false,"openTime":"06:00:00","closeTime":"22:00:00","localTime":"2014-09-24T17:43:12.5998399","openAsOfLocalTime":true,"opensIn":null,"closesIn":"04:16:47"},"currency":"USD"}},{"distance":28.3322,"store":{"id":"10474","name":"Ingles-Waynesville #23","brandName":"Starbucks","phoneNumber":"828-456-7599","operatingStatus":{"operating":true,"openDate":"4/28/2008 12:00:00 AM","closeDate":null,"status":"ACTIVE"},"address":{"streetAddressLine1":"201 Barber Blvd","streetAddressLine2":null,"streetAddressLine3":null,"city":"Waynesville","countrySubdivisionCode":"NC","countryCode":"US","postalCode":"287862872"},"coordinates":{"latitude":35.504061,"longitude":-82.988091},"features":[{"code":"WF","name":"Wireless Hotspot"},{"code":"LB","name":"La Boulange"},{"code":"FZ","name":"Fizzio Handcrafted Beverage"}],"regularHours":{"monday":{"open":true,"open24Hours":false,"openTime":"06:00:00","closeTime":"21:00:00"},"tuesday":{"open":true,"open24Hours":false,"openTime":"06:00:00","closeTime":"21:00:00"},"wednesday":{"open":true,"open24Hours":false,"openTime":"06:00:00","closeTime":"21:00:00"},"thursday":{"open":true,"open24Hours":false,"openTime":"06:00:00","closeTime":"21:00:00"},"friday":{"open":true,"open24Hours":false,"openTime":"06:00:00","closeTime":"21:00:00"},"saturday":{"open":true,"open24Hours":false,"openTime":"06:00:00","closeTime":"21:00:00"},"sunday":{"open":true,"open24Hours":false,"openTime":"07:00:00","closeTime":"21:00:00"},"open24x7":false},"today":{"open":true,"open24Hours":false,"openTime":"06:00:00","closeTime":"21:00:00","localTime":"2014-09-24T17:43:12.5998399","openAsOfLocalTime":true,"opensIn":null,"closesIn":"03:16:47"},"currency":"USD"}},{"distance":33.5762,"store":{"id":"91357","name":"Ingles Cashiers # 110","brandName":"Starbucks","phoneNumber":"828-743-3801","operatingStatus":{"operating":true,"openDate":"9/24/2012 12:00:00 AM","closeDate":null,"status":"ACTIVE"},"address":{"streetAddressLine1":"230 US 64 E","streetAddressLine2":null,"streetAddressLine3":null,"city":"Cashiers","countrySubdivisionCode":"NC","countryCode":"US","postalCode":"28717"},"coordinates":{"latitude":35.11413,"longitude":-83.098566},"features":[{"code":"WA","name":"Oven-warmed Food"},{"code":"WF","name":"Wireless Hotspot"},{"code":"LB","name":"La Boulange"}],"regularHours":{"monday":{"open":true,"open24Hours":false,"openTime":"07:00:00","closeTime":"21:00:00"},"tuesday":{"open":true,"open24Hours":false,"openTime":"07:00:00","closeTime":"21:00:00"},"wednesday":{"open":true,"open24Hours":false,"openTime":"07:00:00","closeTime":"21:00:00"},"thursday":{"open":true,"open24Hours":false,"openTime":"07:00:00","closeTime":"21:00:00"},"friday":{"open":true,"open24Hours":false,"openTime":"07:00:00","closeTime":"21:00:00"},"saturday":{"open":true,"open24Hours":false,"openTime":"07:00:00","closeTime":"21:00:00"},"sunday":{"open":true,"open24Hours":false,"openTime":"07:00:00","closeTime":"21:00:00"},"open24x7":false},"today":{"open":true,"open24Hours":false,"openTime":"07:00:00","closeTime":"21:00:00","localTime":"2014-09-24T17:43:12.5998399","openAsOfLocalTime":true,"opensIn":null,"closesIn":"03:16:47"},"currency":"USD"}},{"distance":33.8298,"store":{"id":"7632","name":"Watkins & Lamar Alexander Pkwy","brandName":"Starbucks","phoneNumber":"865-379-7677","operatingStatus":{"operating":true,"openDate":"7/20/2007 12:00:00 AM","closeDate":null,"status":"ACTIVE"},"address":{"streetAddressLine1":"1011 W Lamar Alexander Pkwy","streetAddressLine2":null,"streetAddressLine3":null,"city":"Maryville","countrySubdivisionCode":"TN","countryCode":"US","postalCode":"378014580"},"coordinates":{"latitude":35.749834,"longitude":-83.992229},"features":[{"code":"WA","name":"Oven-warmed Food"},{"code":"WF","name":"Wireless Hotspot"},{"code":"VS","name":"Verismo"},{"code":"CD","name":"Mobile Payment"},{"code":"DR","name":"Digital Rewards"},{"code":"LB","name":"La Boulange"},{"code":"DT","name":"Drive-Through"}],"regularHours":{"monday":{"open":true,"open24Hours":false,"openTime":"05:30:00","closeTime":"22:00:00"},"tuesday":{"open":true,"open24Hours":false,"openTime":"05:30:00","closeTime":"22:00:00"},"wednesday":{"open":true,"open24Hours":false,"openTime":"05:30:00","closeTime":"22:00:00"},"thursday":{"open":true,"open24Hours":false,"openTime":"05:30:00","closeTime":"22:00:00"},"friday":{"open":true,"open24Hours":false,"openTime":"05:30:00","closeTime":"22:30:00"},"saturday":{"open":true,"open24Hours":false,"openTime":"05:30:00","closeTime":"22:30:00"},"sunday":{"open":true,"open24Hours":false,"openTime":"06:00:00","closeTime":"22:00:00"},"open24x7":false},"today":{"open":true,"open24Hours":false,"openTime":"05:30:00","closeTime":"22:00:00","localTime":"2014-09-24T17:43:12.5998399","openAsOfLocalTime":true,"opensIn":null,"closesIn":"04:16:47"},"currency":"USD"}},{"distance":35.8408,"store":{"id":"7610","name":"TYS Foodcourt (Knoxville)","brandName":"Starbucks","phoneNumber":null,"operatingStatus":{"operating":true,"openDate":"5/26/2009 12:00:00 AM","closeDate":null,"status":"ACTIVE"},"address":{"streetAddressLine1":"2055 Airport Hwy","streetAddressLine2":null,"streetAddressLine3":null,"city":"Alcoa","countrySubdivisionCode":"TN","countryCode":"US","postalCode":"377013316"},"coordinates":{"latitude":35.805814,"longitude":-83.986709},"features":[{"code":"WF","name":"Wireless Hotspot"},{"code":"DR","name":"Digital Rewards"},{"code":"LB","name":"La Boulange"}],"regularHours":{"monday":{"open":true,"open24Hours":false,"openTime":"05:00:00","closeTime":"20:00:00"},"tuesday":{"open":true,"open24Hours":false,"openTime":"05:00:00","closeTime":"20:00:00"},"wednesday":{"open":true,"open24Hours":false,"openTime":"05:00:00","closeTime":"20:00:00"},"thursday":{"open":true,"open24Hours":false,"openTime":"05:00:00","closeTime":"20:00:00"},"friday":{"open":true,"open24Hours":false,"openTime":"05:00:00","closeTime":"20:00:00"},"saturday":{"open":true,"open24Hours":false,"openTime":"05:00:00","closeTime":"20:00:00"},"sunday":{"open":true,"open24Hours":false,"openTime":"05:00:00","closeTime":"17:00:00"},"open24x7":false},"today":{"open":true,"open24Hours":false,"openTime":"05:00:00","closeTime":"20:00:00","localTime":"2014-09-24T17:43:12.5998399","openAsOfLocalTime":true,"opensIn":null,"closesIn":"02:16:47"},"currency":"USD"}},{"distance":35.9524,"store":{"id":"17486","name":"Cusick & Alcoa","brandName":"Starbucks","phoneNumber":"865-982-0642","operatingStatus":{"operating":true,"openDate":"11/18/2006 12:00:00 AM","closeDate":null,"status":"ACTIVE"},"address":{"streetAddressLine1":"121 Cusick Rd","streetAddressLine2":null,"streetAddressLine3":null,"city":"Alcoa","countrySubdivisionCode":"TN","countryCode":"US","postalCode":"377013125"},"coordinates":{"latitude":35.812305,"longitude":-83.98282},"features":[{"code":"WA","name":"Oven-warmed Food"},{"code":"VS","name":"Verismo"},{"code":"CD","name":"Mobile Payment"},{"code":"DR","name":"Digital Rewards"},{"code":"LB","name":"La Boulange"},{"code":"GO","name":"Google Wi-Fi"},{"code":"DT","name":"Drive-Through"}],"regularHours":{"monday":{"open":true,"open24Hours":false,"openTime":"05:00:00","closeTime":"22:30:00"},"tuesday":{"open":true,"open24Hours":false,"openTime":"05:00:00","closeTime":"22:30:00"},"wednesday":{"open":true,"open24Hours":false,"openTime":"05:00:00","closeTime":"22:30:00"},"thursday":{"open":true,"open24Hours":false,"openTime":"05:00:00","closeTime":"22:30:00"},"friday":{"open":true,"open24Hours":false,"openTime":"05:00:00","closeTime":"23:00:00"},"saturday":{"open":true,"open24Hours":false,"openTime":"05:30:00","closeTime":"23:00:00"},"sunday":{"open":true,"open24Hours":false,"openTime":"05:30:00","closeTime":"22:30:00"},"open24x7":false},"today":{"open":true,"open24Hours":false,"openTime":"05:00:00","closeTime":"22:30:00","localTime":"2014-09-24T17:43:12.5998399","openAsOfLocalTime":true,"opensIn":null,"closesIn":"04:46:47"},"currency":"USD"}},{"distance":36.5903,"store":{"id":"7552","name":"Ingles-Canton #55","brandName":"Starbucks","phoneNumber":null,"operatingStatus":{"operating":true,"openDate":"6/28/2009 12:00:00 AM","closeDate":null,"status":"ACTIVE"},"address":{"streetAddressLine1":"630 Champion Dr","streetAddressLine2":null,"streetAddressLine3":null,"city":"Canton","countrySubdivisionCode":"NC","countryCode":"US","postalCode":"287163032"},"coordinates":{"latitude":35.538994,"longitude":-82.8446},"features":[{"code":"WF","name":"Wireless Hotspot"},{"code":"LB","name":"La Boulange"}],"regularHours":{"monday":{"open":true,"open24Hours":false,"openTime":"06:00:00","closeTime":"21:00:00"},"tuesday":{"open":true,"open24Hours":false,"openTime":"06:00:00","closeTime":"21:00:00"},"wednesday":{"open":true,"open24Hours":false,"openTime":"06:00:00","closeTime":"21:00:00"},"thursday":{"open":true,"open24Hours":false,"openTime":"06:00:00","closeTime":"21:00:00"},"friday":{"open":true,"open24Hours":false,"openTime":"06:00:00","closeTime":"21:00:00"},"saturday":{"open":true,"open24Hours":false,"openTime":"06:00:00","closeTime":"21:00:00"},"sunday":{"open":true,"open24Hours":false,"openTime":"07:00:00","closeTime":"21:00:00"},"open24x7":false},"today":{"open":true,"open24Hours":false,"openTime":"06:00:00","closeTime":"21:00:00","localTime":"2014-09-24T17:43:12.5998399","openAsOfLocalTime":true,"opensIn":null,"closesIn":"03:16:47"},"currency":"USD"}},{"distance":39.1463,"store":{"id":"1007125","name":"Ingles Murphy - #25","brandName":"Starbucks","phoneNumber":"828-837-3043","operatingStatus":{"operating":true,"openDate":"4/15/2014 12:00:00 AM","closeDate":null,"status":"ACTIVE"},"address":{"streetAddressLine1":"2060 Hwy 19","streetAddressLine2":null,"streetAddressLine3":null,"city":"Murphy","countrySubdivisionCode":"NC","countryCode":"US","postalCode":"28906"},"coordinates":{"latitude":35.105432,"longitude":-84.009621},"features":[{"code":"LB","name":"La Boulange"}],"regularHours":null,"today":null,"currency":"USD"}},{"distance":39.6623,"store":{"id":"87041","name":"Ingles-Hiawassee #483","brandName":"Starbucks","phoneNumber":"706-896-0093","operatingStatus":{"operating":true,"openDate":"3/5/2012 12:00:00 AM","closeDate":null,"status":"ACTIVE"},"address":{"streetAddressLine1":"94 N Main St","streetAddressLine2":null,"streetAddressLine3":null,"city":"Hiawassee","countrySubdivisionCode":"GA","countryCode":"US","postalCode":"305462254"},"coordinates":{"latitude":34.948902,"longitude":-83.757415},"features":[{"code":"LB","name":"La Boulange"}],"regularHours":{"monday":{"open":true,"open24Hours":false,"openTime":"07:00:00","closeTime":"21:00:00"},"tuesday":{"open":true,"open24Hours":false,"openTime":"07:00:00","closeTime":"21:00:00"},"wednesday":{"open":true,"open24Hours":false,"openTime":"07:00:00","closeTime":"21:00:00"},"thursday":{"open":true,"open24Hours":false,"openTime":"07:00:00","closeTime":"21:00:00"},"friday":{"open":true,"open24Hours":false,"openTime":"07:00:00","closeTime":"21:00:00"},"saturday":{"open":true,"open24Hours":false,"openTime":"07:00:00","closeTime":"21:00:00"},"sunday":{"open":true,"open24Hours":false,"openTime":"07:00:00","closeTime":"21:00:00"},"open24x7":false},"today":{"open":true,"open24Hours":false,"openTime":"07:00:00","closeTime":"21:00:00","localTime":"2014-09-24T17:43:12.5998399","openAsOfLocalTime":true,"opensIn":null,"closesIn":"03:16:47"},"currency":"USD"}},{"distance":40.8362,"store":{"id":"9890","name":"University of Tennessee Student Cen","brandName":"Starbucks","phoneNumber":"865-974-7376","operatingStatus":{"operating":true,"openDate":"7/28/2008 12:00:00 AM","closeDate":null,"status":"ACTIVE"},"address":{"streetAddressLine1":"1235 Phillip Fulmer Way","streetAddressLine2":null,"streetAddressLine3":null,"city":"Knoxville","countrySubdivisionCode":"TN","countryCode":"US","postalCode":"379964511"},"coordinates":{"latitude":35.95431,"longitude":-83.925904},"features":[{"code":"WF","name":"Wireless Hotspot"},{"code":"LB","name":"La Boulange"}],"regularHours":{"monday":{"open":true,"open24Hours":false,"openTime":"07:30:00","closeTime":"20:00:00"},"tuesday":{"open":true,"open24Hours":false,"openTime":"07:30:00","closeTime":"20:00:00"},"wednesday":{"open":true,"open24Hours":false,"openTime":"07:30:00","closeTime":"20:00:00"},"thursday":{"open":true,"open24Hours":false,"openTime":"07:30:00","closeTime":"20:00:00"},"friday":{"open":true,"open24Hours":false,"openTime":"07:30:00","closeTime":"20:00:00"},"saturday":{"open":false,"open24Hours":false,"openTime":"00:00:00","closeTime":"00:00:00"},"sunday":{"open":false,"open24Hours":false,"openTime":"00:00:00","closeTime":"00:00:00"},"open24x7":false},"today":{"open":true,"open24Hours":false,"openTime":"07:30:00","closeTime":"20:00:00","localTime":"2014-09-24T17:43:12.5998399","openAsOfLocalTime":true,"opensIn":null,"closesIn":"02:16:47"},"currency":"USD"}},{"distance":40.9771,"store":{"id":"12960","name":"U of TN/Knoxville - Library","brandName":"Starbucks","phoneNumber":"865-974-6261","operatingStatus":{"operating":true,"openDate":"9/5/2001 12:00:00 AM","closeDate":null,"status":"ACTIVE"},"address":{"streetAddressLine1":"1017 Francis Street","streetAddressLine2":null,"streetAddressLine3":null,"city":"Knoxville","countrySubdivisionCode":"TN","countryCode":"US","postalCode":"379163433"},"coordinates":{"latitude":35.952475,"longitude":-83.933011},"features":[{"code":"WA","name":"Oven-warmed Food"},{"code":"WF","name":"Wireless Hotspot"},{"code":"LB","name":"La Boulange"}],"regularHours":{"monday":{"open":true,"open24Hours":true,"openTime":"00:00:00","closeTime":"00:00:00"},"tuesday":{"open":true,"open24Hours":true,"openTime":"00:00:00","closeTime":"00:00:00"},"wednesday":{"open":true,"open24Hours":true,"openTime":"00:00:00","closeTime":"00:00:00"},"thursday":{"open":true,"open24Hours":true,"openTime":"00:00:00","closeTime":"00:00:00"},"friday":{"open":true,"open24Hours":false,"openTime":"05:00:00","closeTime":"17:00:00"},"saturday":{"open":true,"open24Hours":false,"openTime":"05:00:00","closeTime":"17:00:00"},"sunday":{"open":true,"open24Hours":false,"openTime":"09:00:00","closeTime":"17:00:00"},"open24x7":false},"today":{"open":true,"open24Hours":true,"openTime":"00:00:00","closeTime":"00:00:00","localTime":"2014-09-24T17:43:12.5998399","openAsOfLocalTime":true,"opensIn":null,"closesIn":null},"currency":"USD"}},{"distance":41.1,"store":{"id":"16413","name":"Hilton Knoxville","brandName":"Starbucks","phoneNumber":"865-523-2300","operatingStatus":{"operating":true,"openDate":"4/28/2004 12:00:00 AM","closeDate":null,"status":"ACTIVE"},"address":{"streetAddressLine1":"501 West Church Street","streetAddressLine2":null,"streetAddressLine3":null,"city":"Knoxville","countrySubdivisionCode":"TN","countryCode":"US","postalCode":"379022506"},"coordinates":{"latitude":35.96265,"longitude":-83.919985},"features":[{"code":"WF","name":"Wireless Hotspot"},{"code":"LB","name":"La Boulange"}],"regularHours":{"monday":{"open":true,"open24Hours":false,"openTime":"06:30:00","closeTime":"19:00:00"},"tuesday":{"open":true,"open24Hours":false,"openTime":"06:30:00","closeTime":"19:00:00"},"wednesday":{"open":true,"open24Hours":false,"openTime":"06:30:00","closeTime":"19:00:00"},"thursday":{"open":true,"open24Hours":false,"openTime":"06:30:00","closeTime":"19:00:00"},"friday":{"open":true,"open24Hours":false,"openTime":"06:30:00","closeTime":"19:00:00"},"saturday":{"open":true,"open24Hours":false,"openTime":"06:30:00","closeTime":"19:00:00"},"sunday":{"open":true,"open24Hours":false,"openTime":"07:00:00","closeTime":"15:00:00"},"open24x7":false},"today":{"open":true,"open24Hours":false,"openTime":"06:30:00","closeTime":"19:00:00","localTime":"2014-09-24T17:43:12.5998399","openAsOfLocalTime":true,"opensIn":null,"closesIn":"01:16:47"},"currency":"USD"}},{"distance":41.2564,"store":{"id":"8513","name":"Cumberland Ave & 21st St","brandName":"Starbucks","phoneNumber":"865-673-0843","operatingStatus":{"operating":true,"openDate":"9/30/2005 12:00:00 AM","closeDate":null,"status":"ACTIVE"},"address":{"streetAddressLine1":"2021 Cumberland Avenue","streetAddressLine2":null,"streetAddressLine3":null,"city":"Knoxville","countrySubdivisionCode":"TN","countryCode":"US","postalCode":"379162909"},"coordinates":{"latitude":35.954759,"longitude":-83.937527},"features":[{"code":"WA","name":"Oven-warmed Food"},{"code":"WF","name":"Wireless Hotspot"},{"code":"CD","name":"Mobile Payment"},{"code":"DR","name":"Digital Rewards"},{"code":"LB","name":"La Boulange"},{"code":"DT","name":"Drive-Through"}],"regularHours":{"monday":{"open":true,"open24Hours":false,"openTime":"05:30:00","closeTime":"23:00:00"},"tuesday":{"open":true,"open24Hours":false,"openTime":"05:30:00","closeTime":"23:00:00"},"wednesday":{"open":true,"open24Hours":false,"openTime":"05:30:00","closeTime":"23:00:00"},"thursday":{"open":true,"open24Hours":false,"openTime":"05:30:00","closeTime":"23:00:00"},"friday":{"open":true,"open24Hours":false,"openTime":"05:30:00","closeTime":"23:00:00"},"saturday":{"open":true,"open24Hours":false,"openTime":"05:30:00","closeTime":"23:00:00"},"sunday":{"open":true,"open24Hours":false,"openTime":"05:30:00","closeTime":"23:00:00"},"open24x7":false},"today":{"open":true,"open24Hours":false,"openTime":"05:30:00","closeTime":"23:00:00","localTime":"2014-09-24T17:43:12.5998399","openAsOfLocalTime":true,"opensIn":null,"closesIn":"05:16:47"},"currency":"USD"}},{"distance":41.726,"store":{"id":"19303","name":"Ingles-Clayton #488","brandName":"Starbucks","phoneNumber":"706-782-3365","operatingStatus":{"operating":true,"openDate":"11/8/2010 12:00:00 AM","closeDate":null,"status":"ACTIVE"},"address":{"streetAddressLine1":"176 Highway 441 N","streetAddressLine2":null,"streetAddressLine3":null,"city":"Clayton","countrySubdivisionCode":"GA","countryCode":"US","postalCode":"305254207"},"coordinates":{"latitude":34.880248,"longitude":-83.396549},"features":[{"code":"WF","name":"Wireless Hotspot"},{"code":"LB","name":"La Boulange"}],"regularHours":{"monday":{"open":true,"open24Hours":false,"openTime":"07:00:00","closeTime":"21:00:00"},"tuesday":{"open":true,"open24Hours":false,"openTime":"07:00:00","closeTime":"21:00:00"},"wednesday":{"open":true,"open24Hours":false,"openTime":"07:00:00","closeTime":"21:00:00"},"thursday":{"open":true,"open24Hours":false,"openTime":"07:00:00","closeTime":"21:00:00"},"friday":{"open":true,"open24Hours":false,"openTime":"07:00:00","closeTime":"21:00:00"},"saturday":{"open":true,"open24Hours":false,"openTime":"07:00:00","closeTime":"21:00:00"},"sunday":{"open":true,"open24Hours":false,"openTime":"07:00:00","closeTime":"21:00:00"},"open24x7":false},"today":{"open":true,"open24Hours":false,"openTime":"07:00:00","closeTime":"21:00:00","localTime":"2014-09-24T17:43:12.5998399","openAsOfLocalTime":true,"opensIn":null,"closesIn":"03:16:47"},"currency":"USD"}},{"distance":41.9066,"store":{"id":"18091","name":"Kroger - Knoxville #525","brandName":"Starbucks","phoneNumber":null,"operatingStatus":{"operating":true,"openDate":"5/7/2007 12:00:00 AM","closeDate":null,"status":"ACTIVE"},"address":{"streetAddressLine1":"9501 S. Northshore Dr.","streetAddressLine2":null,"streetAddressLine3":null,"city":"Knoxville","countrySubdivisionCode":"TN","countryCode":"US","postalCode":"379225814"},"coordinates":{"latitude":35.862626,"longitude":-84.069257},"features":[{"code":"WF","name":"Wireless Hotspot"},{"code":"LB","name":"La Boulange"}],"regularHours":{"monday":{"open":true,"open24Hours":false,"openTime":"06:30:00","closeTime":"19:00:00"},"tuesday":{"open":true,"open24Hours":false,"openTime":"06:30:00","closeTime":"19:00:00"},"wednesday":{"open":true,"open24Hours":false,"openTime":"06:30:00","closeTime":"19:00:00"},"thursday":{"open":true,"open24Hours":false,"openTime":"06:30:00","closeTime":"19:00:00"},"friday":{"open":true,"open24Hours":false,"openTime":"06:30:00","closeTime":"19:00:00"},"saturday":{"open":true,"open24Hours":false,"openTime":"06:30:00","closeTime":"19:00:00"},"sunday":{"open":true,"open24Hours":false,"openTime":"07:00:00","closeTime":"19:00:00"},"open24x7":false},"today":{"open":true,"open24Hours":false,"openTime":"06:30:00","closeTime":"19:00:00","localTime":"2014-09-24T17:43:12.5998399","openAsOfLocalTime":true,"opensIn":null,"closesIn":"01:16:47"},"currency":"USD"}},{"distance":42.2234,"store":{"id":"11252","name":"Kingston Pike & Newcomb Ave.","brandName":"Starbucks","phoneNumber":"865-584-2363","operatingStatus":{"operating":true,"openDate":"11/2/2002 12:00:00 AM","closeDate":null,"status":"ACTIVE"},"address":{"streetAddressLine1":"4924 Kingston Pike","streetAddressLine2":null,"streetAddressLine3":null,"city":"Knoxville","countrySubdivisionCode":"TN","countryCode":"US","postalCode":"379195111"},"coordinates":{"latitude":35.940562,"longitude":-83.985672},"features":[{"code":"CL","name":"Starbucks Reserve-Clover Brewed"},{"code":"WA","name":"Oven-warmed Food"},{"code":"VS","name":"Verismo"},{"code":"CD","name":"Mobile Payment"},{"code":"DR","name":"Digital Rewards"},{"code":"LB","name":"La Boulange"},{"code":"GO","name":"Google Wi-Fi"},{"code":"DT","name":"Drive-Through"}],"regularHours":{"monday":{"open":true,"open24Hours":false,"openTime":"05:30:00","closeTime":"22:00:00"},"tuesday":{"open":true,"open24Hours":false,"openTime":"05:30:00","closeTime":"22:00:00"},"wednesday":{"open":true,"open24Hours":false,"openTime":"05:30:00","closeTime":"22:00:00"},"thursday":{"open":true,"open24Hours":false,"openTime":"05:30:00","closeTime":"22:00:00"},"friday":{"open":true,"open24Hours":false,"openTime":"05:30:00","closeTime":"23:00:00"},"saturday":{"open":true,"open24Hours":false,"openTime":"05:30:00","closeTime":"23:00:00"},"sunday":{"open":true,"open24Hours":false,"openTime":"06:30:00","closeTime":"22:00:00"},"open24x7":false},"today":{"open":true,"open24Hours":false,"openTime":"05:30:00","closeTime":"22:00:00","localTime":"2014-09-24T17:43:12.5998399","openAsOfLocalTime":true,"opensIn":null,"closesIn":"04:16:47"},"currency":"USD"}},{"distance":43.4517,"store":{"id":"116511","name":"West Town Mall Kiosk","brandName":"Starbucks","phoneNumber":"8655317894","operatingStatus":{"operating":true,"openDate":"5/2/2013 12:00:00 AM","closeDate":null,"status":"ACTIVE"},"address":{"streetAddressLine1":"7600 Kingston Pike","streetAddressLine2":null,"streetAddressLine3":null,"city":"Knoxville","countrySubdivisionCode":"TN","countryCode":"US","postalCode":"37919"},"coordinates":{"latitude":35.925036,"longitude":-84.037726},"features":[{"code":"WA","name":"Oven-warmed Food"},{"code":"WF","name":"Wireless Hotspot"},{"code":"CD","name":"Mobile Payment"},{"code":"DR","name":"Digital Rewards"},{"code":"LB","name":"La Boulange"}],"regularHours":{"monday":{"open":true,"open24Hours":false,"openTime":"08:30:00","closeTime":"21:00:00"},"tuesday":{"open":true,"open24Hours":false,"openTime":"08:30:00","closeTime":"21:00:00"},"wednesday":{"open":true,"open24Hours":false,"openTime":"08:30:00","closeTime":"21:00:00"},"thursday":{"open":true,"open24Hours":false,"openTime":"08:30:00","closeTime":"21:00:00"},"friday":{"open":true,"open24Hours":false,"openTime":"08:30:00","closeTime":"21:00:00"},"saturday":{"open":true,"open24Hours":false,"openTime":"08:30:00","closeTime":"21:00:00"},"sunday":{"open":true,"open24Hours":false,"openTime":"10:30:00","closeTime":"18:00:00"},"open24x7":false},"today":{"open":true,"open24Hours":false,"openTime":"08:30:00","closeTime":"21:00:00","localTime":"2014-09-24T17:43:12.5998399","openAsOfLocalTime":true,"opensIn":null,"closesIn":"03:16:47"},"currency":"USD"}},{"distance":43.6457,"store":{"id":"7874","name":"Kingston Pike & Montvue","brandName":"Starbucks","phoneNumber":"(865) 470-9234","operatingStatus":{"operating":true,"openDate":"5/11/2007 12:00:00 AM","closeDate":null,"status":"ACTIVE"},"address":{"streetAddressLine1":"7803 Montvue Center Way","streetAddressLine2":null,"streetAddressLine3":null,"city":"Knoxville","countrySubdivisionCode":"TN","countryCode":"US","postalCode":"379195575"},"coordinates":{"latitude":35.925152,"longitude":-84.04244},"features":[{"code":"WA","name":"Oven-warmed Food"},{"code":"WF","name":"Wireless Hotspot"},{"code":"VS","name":"Verismo"},{"code":"CD","name":"Mobile Payment"},{"code":"DR","name":"Digital Rewards"},{"code":"LB","name":"La Boulange"},{"code":"DT","name":"Drive-Through"}],"regularHours":{"monday":{"open":true,"open24Hours":false,"openTime":"05:30:00","closeTime":"22:00:00"},"tuesday":{"open":true,"open24Hours":false,"openTime":"05:30:00","closeTime":"22:00:00"},"wednesday":{"open":true,"open24Hours":false,"openTime":"05:30:00","closeTime":"22:00:00"},"thursday":{"open":true,"open24Hours":false,"openTime":"05:30:00","closeTime":"22:00:00"},"friday":{"open":true,"open24Hours":false,"openTime":"05:30:00","closeTime":"23:00:00"},"saturday":{"open":true,"open24Hours":false,"openTime":"05:30:00","closeTime":"23:00:00"},"sunday":{"open":true,"open24Hours":false,"openTime":"06:00:00","closeTime":"22:00:00"},"open24x7":false},"today":{"open":true,"open24Hours":false,"openTime":"05:30:00","closeTime":"22:00:00","localTime":"2014-09-24T17:43:12.5998399","openAsOfLocalTime":true,"opensIn":null,"closesIn":"04:16:47"},"currency":"USD"}},{"distance":43.7661,"store":{"id":"1006801","name":"Target Knoxville West T-151","brandName":"Starbucks","phoneNumber":"865-293-2203","operatingStatus":{"operating":true,"openDate":"3/17/2014 12:00:00 AM","closeDate":null,"status":"ACTIVE"},"address":{"streetAddressLine1":"8040 Ray Mears Blvd","streetAddressLine2":null,"streetAddressLine3":null,"city":"Knoxville West","countrySubdivisionCode":"TN","countryCode":"US","postalCode":"37919"},"coordinates":{"latitude":35.922993,"longitude":-84.048018},"features":[{"code":"LB","name":"La Boulange"}],"regularHours":null,"today":null,"currency":"USD"}},{"distance":43.8103,"store":{"id":"89781","name":"Target Knoxville T-2815","brandName":"Starbucks","phoneNumber":"865-671-0912","operatingStatus":{"operating":true,"openDate":"7/24/2012 12:00:00 AM","closeDate":null,"status":"ACTIVE"},"address":{"streetAddressLine1":"1900 Town Center Blvd","streetAddressLine2":null,"streetAddressLine3":null,"city":"Knoxville","countrySubdivisionCode":"TN","countryCode":"US","postalCode":"37922"},"coordinates":{"latitude":35.871502,"longitude":-84.10386},"features":[{"code":"LB","name":"La Boulange"}],"regularHours":null,"today":null,"currency":"USD"}},{"distance":44.4189,"store":{"id":"8405","name":"Target Knoxville North T-2057","brandName":"Starbucks","phoneNumber":"865-291-0086","operatingStatus":{"operating":true,"openDate":"7/18/2006 12:00:00 AM","closeDate":null,"status":"ACTIVE"},"address":{"streetAddressLine1":"4700 New Harvest Ln","streetAddressLine2":null,"streetAddressLine3":null,"city":"Knoxville","countrySubdivisionCode":"TN","countryCode":"US","postalCode":"379187000"},"coordinates":{"latitude":36.036851,"longitude":-83.888743},"features":[{"code":"CD","name":"Mobile Payment"},{"code":"LB","name":"La Boulange"}],"regularHours":{"monday":{"open":true,"open24Hours":false,"openTime":"08:00:00","closeTime":"21:00:00"},"tuesday":{"open":true,"open24Hours":false,"openTime":"08:00:00","closeTime":"21:00:00"},"wednesday":{"open":true,"open24Hours":false,"openTime":"08:00:00","closeTime":"21:00:00"},"thursday":{"open":true,"open24Hours":false,"openTime":"08:00:00","closeTime":"21:00:00"},"friday":{"open":true,"open24Hours":false,"openTime":"08:00:00","closeTime":"21:00:00"},"saturday":{"open":true,"open24Hours":false,"openTime":"08:00:00","closeTime":"21:00:00"},"sunday":{"open":true,"open24Hours":false,"openTime":"08:00:00","closeTime":"20:00:00"},"open24x7":false},"today":{"open":true,"open24Hours":false,"openTime":"08:00:00","closeTime":"21:00:00","localTime":"2014-09-24T17:43:12.5998399","openAsOfLocalTime":true,"opensIn":null,"closesIn":"03:16:47"},"currency":"USD"}},{"distance":44.8714,"store":{"id":"89238","name":"Kroger-Knoxville #684","brandName":"Starbucks","phoneNumber":"865-985-7960","operatingStatus":{"operating":true,"openDate":"6/27/2012 12:00:00 AM","closeDate":null,"status":"ACTIVE"},"address":{"streetAddressLine1":"9225 Kingston Rd.","streetAddressLine2":null,"streetAddressLine3":null,"city":"Knoxville","countrySubdivisionCode":"TN","countryCode":"US","postalCode":"379223660"},"coordinates":{"latitude":35.911527,"longitude":-84.087783},"features":[{"code":"LB","name":"La Boulange"}],"regularHours":null,"today":null,"currency":"USD"}},{"distance":45.0016,"store":{"id":"1005212","name":"Kingston Pike at Sherrill Hill","brandName":"Starbucks","phoneNumber":"8656907053","operatingStatus":{"operating":true,"openDate":"6/8/2013 12:00:00 AM","closeDate":null,"status":"ACTIVE"},"address":{"streetAddressLine1":"115 Moss Grove Blvd.","streetAddressLine2":null,"streetAddressLine3":null,"city":"Knoxville","countrySubdivisionCode":"TN","countryCode":"US","postalCode":"37922"},"coordinates":{"latitude":35.909352,"longitude":-84.093195},"features":[{"code":"CL","name":"Starbucks Reserve-Clover Brewed"},{"code":"WA","name":"Oven-warmed Food"},{"code":"CD","name":"Mobile Payment"},{"code":"DR","name":"Digital Rewards"},{"code":"LB","name":"La Boulange"},{"code":"GO","name":"Google Wi-Fi"},{"code":"DT","name":"Drive-Through"}],"regularHours":{"monday":{"open":true,"open24Hours":false,"openTime":"05:30:00","closeTime":"22:00:00"},"tuesday":{"open":true,"open24Hours":false,"openTime":"05:30:00","closeTime":"22:00:00"},"wednesday":{"open":true,"open24Hours":false,"openTime":"05:30:00","closeTime":"22:00:00"},"thursday":{"open":true,"open24Hours":false,"openTime":"05:30:00","closeTime":"22:00:00"},"friday":{"open":true,"open24Hours":false,"openTime":"05:30:00","closeTime":"22:00:00"},"saturday":{"open":true,"open24Hours":false,"openTime":"06:00:00","closeTime":"22:00:00"},"sunday":{"open":true,"open24Hours":false,"openTime":"06:00:00","closeTime":"21:00:00"},"open24x7":false},"today":{"open":true,"open24Hours":false,"openTime":"05:30:00","closeTime":"22:00:00","localTime":"2014-09-24T17:43:12.5998399","openAsOfLocalTime":true,"opensIn":null,"closesIn":"04:16:47"},"currency":"USD"}},{"distance":45.4301,"store":{"id":"9470","name":"I-75 @ Merchant Rd","brandName":"Starbucks","phoneNumber":"865-688-2891","operatingStatus":{"operating":true,"openDate":"9/24/2005 12:00:00 AM","closeDate":null,"status":"ACTIVE"},"address":{"streetAddressLine1":"116 Merchants Drive","streetAddressLine2":null,"streetAddressLine3":null,"city":"Knoxville","countrySubdivisionCode":"TN","countryCode":"US","postalCode":"379123501"},"coordinates":{"latitude":36.010384,"longitude":-83.970541},"features":[{"code":"WA","name":"Oven-warmed Food"},{"code":"WF","name":"Wireless Hotspot"},{"code":"VS","name":"Verismo"},{"code":"CD","name":"Mobile Payment"},{"code":"DR","name":"Digital Rewards"},{"code":"LB","name":"La Boulange"},{"code":"DT","name":"Drive-Through"}],"regularHours":{"monday":{"open":true,"open24Hours":false,"openTime":"05:30:00","closeTime":"22:00:00"},"tuesday":{"open":true,"open24Hours":false,"openTime":"05:30:00","closeTime":"22:00:00"},"wednesday":{"open":true,"open24Hours":false,"openTime":"05:30:00","closeTime":"22:00:00"},"thursday":{"open":true,"open24Hours":false,"openTime":"05:30:00","closeTime":"22:00:00"},"friday":{"open":true,"open24Hours":false,"openTime":"05:30:00","closeTime":"23:00:00"},"saturday":{"open":true,"open24Hours":false,"openTime":"05:30:00","closeTime":"23:00:00"},"sunday":{"open":true,"open24Hours":false,"openTime":"06:00:00","closeTime":"22:00:00"},"open24x7":false},"today":{"open":true,"open24Hours":false,"openTime":"05:30:00","closeTime":"22:00:00","localTime":"2014-09-24T17:43:12.5998399","openAsOfLocalTime":true,"opensIn":null,"closesIn":"04:16:47"},"currency":"USD"}},{"distance":45.5417,"store":{"id":"11993","name":"N Cedar Bluff & Park West Blvd","brandName":"Starbucks","phoneNumber":"865-691-2712","operatingStatus":{"operating":true,"openDate":"3/28/2004 12:00:00 AM","closeDate":null,"status":"ACTIVE"},"address":{"streetAddressLine1":"329 N Cedar Bluff Blvd","streetAddressLine2":null,"streetAddressLine3":null,"city":"Knoxville","countrySubdivisionCode":"TN","countryCode":"US","postalCode":"379234507"},"coordinates":{"latitude":35.921411,"longitude":-84.092995},"features":[{"code":"CL","name":"Starbucks Reserve-Clover Brewed"},{"code":"WA","name":"Oven-warmed Food"},{"code":"WF","name":"Wireless Hotspot"},{"code":"VS","name":"Verismo"},{"code":"CD","name":"Mobile Payment"},{"code":"DR","name":"Digital Rewards"},{"code":"LB","name":"La Boulange"},{"code":"DT","name":"Drive-Through"}],"regularHours":{"monday":{"open":true,"open24Hours":false,"openTime":"05:30:00","closeTime":"22:00:00"},"tuesday":{"open":true,"open24Hours":false,"openTime":"05:30:00","closeTime":"22:00:00"},"wednesday":{"open":true,"open24Hours":false,"openTime":"05:30:00","closeTime":"22:00:00"},"thursday":{"open":true,"open24Hours":false,"openTime":"05:30:00","closeTime":"22:00:00"},"friday":{"open":true,"open24Hours":false,"openTime":"05:30:00","closeTime":"23:00:00"},"saturday":{"open":true,"open24Hours":false,"openTime":"05:30:00","closeTime":"23:00:00"},"sunday":{"open":true,"open24Hours":false,"openTime":"06:00:00","closeTime":"22:00:00"},"open24x7":false},"today":{"open":true,"open24Hours":false,"openTime":"05:30:00","closeTime":"22:00:00","localTime":"2014-09-24T17:43:12.5998399","openAsOfLocalTime":true,"opensIn":null,"closesIn":"04:16:47"},"currency":"USD"}},{"distance":45.7651,"store":{"id":"92869","name":"Ingles Farragut # 91","brandName":"Starbucks","phoneNumber":"865-777-4360","operatingStatus":{"operating":true,"openDate":"11/12/2012 12:00:00 AM","closeDate":null,"status":"ACTIVE"},"address":{"streetAddressLine1":"11817 Kingston Pike","streetAddressLine2":null,"streetAddressLine3":null,"city":"Farragut","countrySubdivisionCode":"TN","countryCode":"US","postalCode":"37934"},"coordinates":{"latitude":35.903676,"longitude":-84.116882},"features":[{"code":"LB","name":"La Boulange"}],"regularHours":null,"today":null,"currency":"USD"}},{"distance":46.1405,"store":{"id":"9678","name":"Ingles-Brevard #67","brandName":"Starbucks","phoneNumber":"828-883-2377","operatingStatus":{"operating":true,"openDate":"5/28/2005 12:00:00 AM","closeDate":null,"status":"ACTIVE"},"address":{"streetAddressLine1":"710 N Broad St","streetAddressLine2":null,"streetAddressLine3":null,"city":"Brevard","countrySubdivisionCode":"NC","countryCode":"US","postalCode":"287123102"},"coordinates":{"latitude":35.24057,"longitude":-82.727133},"features":[{"code":"WF","name":"Wireless Hotspot"},{"code":"LB","name":"La Boulange"}],"regularHours":{"monday":{"open":true,"open24Hours":false,"openTime":"06:00:00","closeTime":"21:00:00"},"tuesday":{"open":true,"open24Hours":false,"openTime":"06:00:00","closeTime":"21:00:00"},"wednesday":{"open":true,"open24Hours":false,"openTime":"06:00:00","closeTime":"21:00:00"},"thursday":{"open":true,"open24Hours":false,"openTime":"06:00:00","closeTime":"21:00:00"},"friday":{"open":true,"open24Hours":false,"openTime":"06:00:00","closeTime":"21:00:00"},"saturday":{"open":true,"open24Hours":false,"openTime":"06:00:00","closeTime":"21:00:00"},"sunday":{"open":true,"open24Hours":false,"openTime":"07:00:00","closeTime":"21:00:00"},"open24x7":false},"today":{"open":true,"open24Hours":false,"openTime":"06:00:00","closeTime":"21:00:00","localTime":"2014-09-24T17:43:12.5998399","openAsOfLocalTime":true,"opensIn":null,"closesIn":"03:16:47"},"currency":"USD"}},{"distance":46.3096,"store":{"id":"87106","name":"Kroger-Fountain City  #698","brandName":"Starbucks","phoneNumber":"865-686-1015","operatingStatus":{"operating":true,"openDate":"3/12/2012 12:00:00 AM","closeDate":null,"status":"ACTIVE"},"address":{"streetAddressLine1":"5201 N Broadway St & Knox Rd","streetAddressLine2":null,"streetAddressLine3":null,"city":"Fountain City","countrySubdivisionCode":"TN","countryCode":"US","postalCode":"37918"},"coordinates":{"latitude":36.051167,"longitude":-83.924807},"features":[{"code":"LB","name":"La Boulange"}],"regularHours":null,"today":null,"currency":"USD"}},{"distance":46.5498,"store":{"id":"18090","name":"Kroger - Knoxville #530","brandName":"Starbucks","phoneNumber":null,"operatingStatus":{"operating":true,"openDate":"5/7/2007 12:00:00 AM","closeDate":null,"status":"ACTIVE"},"address":{"streetAddressLine1":"9161 Middlebrook Pike","streetAddressLine2":null,"streetAddressLine3":null,"city":"Knoxville","countrySubdivisionCode":"TN","countryCode":"US","postalCode":"379231438"},"coordinates":{"latitude":35.942573,"longitude":-84.09361},"features":[{"code":"WF","name":"Wireless Hotspot"},{"code":"LB","name":"La Boulange"}],"regularHours":{"monday":{"open":true,"open24Hours":false,"openTime":"06:00:00","closeTime":"20:00:00"},"tuesday":{"open":true,"open24Hours":false,"openTime":"06:00:00","closeTime":"20:00:00"},"wednesday":{"open":true,"open24Hours":false,"openTime":"06:00:00","closeTime":"20:00:00"},"thursday":{"open":true,"open24Hours":false,"openTime":"06:00:00","closeTime":"20:00:00"},"friday":{"open":true,"open24Hours":false,"openTime":"06:00:00","closeTime":"20:00:00"},"saturday":{"open":true,"open24Hours":false,"openTime":"07:00:00","closeTime":"20:00:00"},"sunday":{"open":true,"open24Hours":false,"openTime":"07:00:00","closeTime":"20:00:00"},"open24x7":false},"today":{"open":true,"open24Hours":false,"openTime":"06:00:00","closeTime":"20:00:00","localTime":"2014-09-24T17:43:12.5998399","openAsOfLocalTime":true,"opensIn":null,"closesIn":"02:16:47"},"currency":"USD"}},{"distance":47.1397,"store":{"id":"11335","name":"Super Target Knoxville ST-1370","brandName":"Starbucks","phoneNumber":"865-675-8200","operatingStatus":{"operating":true,"openDate":"3/5/2002 12:00:00 AM","closeDate":null,"status":"ACTIVE"},"address":{"streetAddressLine1":"11100 Parkside Dr","streetAddressLine2":null,"streetAddressLine3":null,"city":"Knoxville","countrySubdivisionCode":"TN","countryCode":"US","postalCode":"379341960"},"coordinates":{"latitude":35.900115,"longitude":-84.151686},"features":[{"code":"CD","name":"Mobile Payment"},{"code":"LB","name":"La Boulange"}],"regularHours":{"monday":{"open":true,"open24Hours":false,"openTime":"08:00:00","closeTime":"21:00:00"},"tuesday":{"open":true,"open24Hours":false,"openTime":"08:00:00","closeTime":"21:00:00"},"wednesday":{"open":true,"open24Hours":false,"openTime":"08:00:00","closeTime":"21:00:00"},"thursday":{"open":true,"open24Hours":false,"openTime":"08:00:00","closeTime":"21:00:00"},"friday":{"open":true,"open24Hours":false,"openTime":"08:00:00","closeTime":"21:00:00"},"saturday":{"open":true,"open24Hours":false,"openTime":"08:00:00","closeTime":"21:00:00"},"sunday":{"open":true,"open24Hours":false,"openTime":"08:00:00","closeTime":"20:00:00"},"open24x7":false},"today":{"open":true,"open24Hours":false,"openTime":"08:00:00","closeTime":"21:00:00","localTime":"2014-09-24T17:43:12.5998399","openAsOfLocalTime":true,"opensIn":null,"closesIn":"03:16:47"},"currency":"USD"}},{"distance":47.1822,"store":{"id":"13783","name":"Parkside Dr--Turkey Creek","brandName":"Starbucks","phoneNumber":"865-675-1529","operatingStatus":{"operating":true,"openDate":"9/20/2003 12:00:00 AM","closeDate":null,"status":"ACTIVE"},"address":{"streetAddressLine1":"11038 Park Side Dr","streetAddressLine2":null,"streetAddressLine3":null,"city":"Knoxville","countrySubdivisionCode":"TN","countryCode":"US","postalCode":"379341952"},"coordinates":{"latitude":35.902066,"longitude":-84.150789},"features":[{"code":"CL","name":"Starbucks Reserve-Clover Brewed"},{"code":"WA","name":"Oven-warmed Food"},{"code":"WF","name":"Wireless Hotspot"},{"code":"VS","name":"Verismo"},{"code":"CD","name":"Mobile Payment"},{"code":"DR","name":"Digital Rewards"},{"code":"LB","name":"La Boulange"},{"code":"DT","name":"Drive-Through"}],"regularHours":{"monday":{"open":true,"open24Hours":false,"openTime":"05:30:00","closeTime":"23:00:00"},"tuesday":{"open":true,"open24Hours":false,"openTime":"05:30:00","closeTime":"23:00:00"},"wednesday":{"open":true,"open24Hours":false,"openTime":"05:30:00","closeTime":"23:00:00"},"thursday":{"open":true,"open24Hours":false,"openTime":"05:30:00","closeTime":"23:00:00"},"friday":{"open":true,"open24Hours":false,"openTime":"05:30:00","closeTime":"00:00:00"},"saturday":{"open":true,"open24Hours":false,"openTime":"05:30:00","closeTime":"00:00:00"},"sunday":{"open":true,"open24Hours":false,"openTime":"06:00:00","closeTime":"23:00:00"},"open24x7":false},"today":{"open":true,"open24Hours":false,"openTime":"05:30:00","closeTime":"23:00:00","localTime":"2014-09-24T17:43:12.5998399","openAsOfLocalTime":true,"opensIn":null,"closesIn":"05:16:47"},"currency":"USD"}},{"distance":47.1957,"store":{"id":"10709","name":"Kroger-Farragut, TN #686","brandName":"Starbucks","phoneNumber":"865-671-7910","operatingStatus":{"operating":true,"openDate":"10/5/2008 12:00:00 AM","closeDate":null,"status":"ACTIVE"},"address":{"streetAddressLine1":"189 Brooklawn Street","streetAddressLine2":null,"streetAddressLine3":null,"city":"Farragut","countrySubdivisionCode":"TN","countryCode":"US","postalCode":"379342875"},"coordinates":{"latitude":35.8757,"longitude":-84.175},"features":[{"code":"WF","name":"Wireless Hotspot"},{"code":"LB","name":"La Boulange"}],"regularHours":{"monday":{"open":true,"open24Hours":false,"openTime":"06:00:00","closeTime":"19:00:00"},"tuesday":{"open":true,"open24Hours":false,"openTime":"06:00:00","closeTime":"19:00:00"},"wednesday":{"open":true,"open24Hours":false,"openTime":"06:00:00","closeTime":"19:00:00"},"thursday":{"open":true,"open24Hours":false,"openTime":"06:00:00","closeTime":"19:00:00"},"friday":{"open":true,"open24Hours":false,"openTime":"06:00:00","closeTime":"19:00:00"},"saturday":{"open":true,"open24Hours":false,"openTime":"07:00:00","closeTime":"19:00:00"},"sunday":{"open":true,"open24Hours":false,"openTime":"07:00:00","closeTime":"19:00:00"},"open24x7":false},"today":{"open":true,"open24Hours":false,"openTime":"06:00:00","closeTime":"19:00:00","localTime":"2014-09-24T17:43:12.5998399","openAsOfLocalTime":true,"opensIn":null,"closesIn":"01:16:47"},"currency":"USD"}},{"distance":48.548,"store":{"id":"91139","name":"Ingles - Powell #399","brandName":"Starbucks","phoneNumber":"865-947-4523","operatingStatus":{"operating":true,"openDate":"9/17/2012 12:00:00 AM","closeDate":null,"status":"ACTIVE"},"address":{"streetAddressLine1":"430 E Emory Rd","streetAddressLine2":null,"streetAddressLine3":null,"city":"Powell","countrySubdivisionCode":"TN","countryCode":"US","postalCode":"37849"},"coordinates":{"latitude":36.049251,"longitude":-83.999464},"features":[{"code":"LB","name":"La Boulange"}],"regularHours":null,"today":null,"currency":"USD"}},{"distance":48.5956,"store":{"id":"16994","name":"I-75 & Emory","brandName":"Starbucks","phoneNumber":"(865) 947-8801","operatingStatus":{"operating":true,"openDate":"6/15/2007 12:00:00 AM","closeDate":null,"status":"ACTIVE"},"address":{"streetAddressLine1":"401 East Emory Road","streetAddressLine2":null,"streetAddressLine3":null,"city":"Powell","countrySubdivisionCode":"TN","countryCode":"US","postalCode":"378493518"},"coordinates":{"latitude":36.049863,"longitude":-83.999876},"features":[{"code":"WA","name":"Oven-warmed Food"},{"code":"WF","name":"Wireless Hotspot"},{"code":"VS","name":"Verismo"},{"code":"CD","name":"Mobile Payment"},{"code":"DR","name":"Digital Rewards"},{"code":"LB","name":"La Boulange"},{"code":"DT","name":"Drive-Through"}],"regularHours":{"monday":{"open":true,"open24Hours":false,"openTime":"05:30:00","closeTime":"22:00:00"},"tuesday":{"open":true,"open24Hours":false,"openTime":"05:30:00","closeTime":"22:00:00"},"wednesday":{"open":true,"open24Hours":false,"openTime":"05:30:00","closeTime":"22:00:00"},"thursday":{"open":true,"open24Hours":false,"openTime":"05:30:00","closeTime":"22:00:00"},"friday":{"open":true,"open24Hours":false,"openTime":"05:30:00","closeTime":"23:00:00"},"saturday":{"open":true,"open24Hours":false,"openTime":"06:00:00","closeTime":"23:00:00"},"sunday":{"open":true,"open24Hours":false,"openTime":"06:00:00","closeTime":"22:00:00"},"open24x7":false},"today":{"open":true,"open24Hours":false,"openTime":"05:30:00","closeTime":"22:00:00","localTime":"2014-09-24T17:43:12.5998399","openAsOfLocalTime":true,"opensIn":null,"closesIn":"04:16:47"},"currency":"USD"}},{"distance":49.0374,"store":{"id":"1005931","name":"Ingles Blairsville #98","brandName":"Starbucks","phoneNumber":"706-745-9862","operatingStatus":{"operating":true,"openDate":"9/25/2013 12:00:00 AM","closeDate":null,"status":"ACTIVE"},"address":{"streetAddressLine1":"43B Hwy 515","streetAddressLine2":null,"streetAddressLine3":null,"city":"Blairsville","countrySubdivisionCode":"GA","countryCode":"US","postalCode":"30512"},"coordinates":{"latitude":34.880413,"longitude":-83.954696},"features":[{"code":"LB","name":"La Boulange"}],"regularHours":null,"today":null,"currency":"USD"}},{"distance":49.2281,"store":{"id":"7553","name":"Ingles-Asheville #62","brandName":"Starbucks","phoneNumber":null,"operatingStatus":{"operating":true,"openDate":"6/28/2009 12:00:00 AM","closeDate":null,"status":"ACTIVE"},"address":{"streetAddressLine1":"575 New Leicester Hwy","streetAddressLine2":null,"streetAddressLine3":null,"city":"Asheville","countrySubdivisionCode":"NC","countryCode":"US","postalCode":"288062122"},"coordinates":{"latitude":35.614112,"longitude":-82.631457},"features":[{"code":"WF","name":"Wireless Hotspot"},{"code":"LB","name":"La Boulange"}],"regularHours":{"monday":{"open":true,"open24Hours":false,"openTime":"06:00:00","closeTime":"21:00:00"},"tuesday":{"open":true,"open24Hours":false,"openTime":"06:00:00","closeTime":"21:00:00"},"wednesday":{"open":true,"open24Hours":false,"openTime":"06:00:00","closeTime":"21:00:00"},"thursday":{"open":true,"open24Hours":false,"openTime":"06:00:00","closeTime":"21:00:00"},"friday":{"open":true,"open24Hours":false,"openTime":"06:00:00","closeTime":"21:00:00"},"saturday":{"open":true,"open24Hours":false,"openTime":"06:00:00","closeTime":"21:00:00"},"sunday":{"open":true,"open24Hours":false,"openTime":"07:00:00","closeTime":"21:00:00"},"open24x7":false},"today":{"open":true,"open24Hours":false,"openTime":"06:00:00","closeTime":"21:00:00","localTime":"2014-09-24T17:43:12.5998399","openAsOfLocalTime":true,"opensIn":null,"closesIn":"03:16:47"},"currency":"USD"}},{"distance":49.8999,"store":{"id":"116417","name":"Ingles Morristown # 85","brandName":"Starbucks","phoneNumber":"423-587-3400","operatingStatus":{"operating":true,"openDate":"3/14/2013 12:00:00 AM","closeDate":null,"status":"ACTIVE"},"address":{"streetAddressLine1":"3980 W. Andrew Johnson Hwy.","streetAddressLine2":null,"streetAddressLine3":null,"city":"Morristown","countrySubdivisionCode":"TN","countryCode":"US","postalCode":"37814"},"coordinates":{"latitude":36.195551,"longitude":-83.350988},"features":[{"code":"LB","name":"La Boulange"}],"regularHours":null,"today":null,"currency":"USD"}}]}
